iflow_mcp_wpfleger96_pagerduty_mcp_server-3.1.1.dist-info/licenses/LICENSE
pagerduty_mcp_server/__init__.py
pagerduty_mcp_server/__main__.py
pagerduty_mcp_server/client.py
pagerduty_mcp_server/escalation_policies.py
pagerduty_mcp_server/incidents.py
pagerduty_mcp_server/oncalls.py
pagerduty_mcp_server/prompts.py
pagerduty_mcp_server/schedules.py
pagerduty_mcp_server/server.py
pagerduty_mcp_server/services.py
pagerduty_mcp_server/teams.py
pagerduty_mcp_server/users.py
pagerduty_mcp_server/utils.py
pagerduty_mcp_server/parsers/__init__.py
pagerduty_mcp_server/parsers/escalation_policy_parser.py
pagerduty_mcp_server/parsers/incident_parser.py
pagerduty_mcp_server/parsers/notes_parser.py
pagerduty_mcp_server/parsers/oncall_parser.py
pagerduty_mcp_server/parsers/parser_helpers.py
pagerduty_mcp_server/parsers/schedule_parser.py
pagerduty_mcp_server/parsers/service_parser.py
pagerduty_mcp_server/parsers/team_parser.py
pagerduty_mcp_server/parsers/user_parser.py
iflow_mcp_wpfleger96_pagerduty_mcp_server-3.1.1.dist-info/METADATA
iflow_mcp_wpfleger96_pagerduty_mcp_server-3.1.1.dist-info/WHEEL
iflow_mcp_wpfleger96_pagerduty_mcp_server-3.1.1.dist-info/entry_points.txt
iflow_mcp_wpfleger96_pagerduty_mcp_server-3.1.1.dist-info/top_level.txt
iflow_mcp_wpfleger96_pagerduty_mcp_server-3.1.1.dist-info/RECORD
